CHANGELOG.md
resource/index.html
resource/matrix.html
ticket_cross_check/__init__.py
ticket_cross_check/__main__.py
ticket_cross_check/__version__.py
ticket_cross_check/gitlab_connector.py
ticket_cross_check/gitlab_models.py
ticket_cross_check/issue_finder.py
ticket_cross_check/matcher.py
ticket_cross_check/models.py
ticket_cross_check/test_gitlab_connector.py
ticket_cross_check/test_gitlab_models.py
ticket_cross_check/test_issue_finder.py
ticket_cross_check/test_matcher.py
ticket_cross_check-0.10.1.dist-info/entry_points.txt
ticket_cross_check-0.10.1.dist-info/WHEEL
ticket_cross_check-0.10.1.dist-info/METADATA
ticket_cross_check-0.10.1.dist-info/RECORD
