Metadata-Version: 2.1
Name: ticket_cross_check
Version: 0.10.1
Summary: Gitlab issue cross checker. Checks for gitlab tickets to appear in the source and vice versa.
License: MIT
Author-email: Christoph Becker <christoph.becker@exb.de>
Requires-Python: >=3.9
Requires-Dist: flit>=3.7.1
Requires-Dist: loguru==0.6.0
Requires-Dist: pydantic==1.9.1
Requires-Dist: python-decouple>=3.6
Requires-Dist: python-gitlab==3.7.0
Requires-Dist: requests>=2.28.1
